reader/__init__.py
reader/__main__.py
reader/config.cfg
reader/feed.py
reader/viewer.py
setopati_reader-2.0.0.dist-info/LICENSE
setopati_reader-2.0.0.dist-info/METADATA
setopati_reader-2.0.0.dist-info/WHEEL
setopati_reader-2.0.0.dist-info/entry_points.txt
setopati_reader-2.0.0.dist-info/top_level.txt
setopati_reader-2.0.0.dist-info/RECORD
