Metadata-Version: 2.1
Name: setopati-reader
Version: 2.0.0
Summary: Read the latest news from setopati
Home-page: https://github.com/jitenpu/setopati-reader
Author: Jitendra
Author-email: UNKNOWN
License: MIT
Platform: UNKNOWN
Classifier: License :: OSI Approved :: MIT License
Classifier: Programming Language :: Python
Classifier: Programming Language :: Python :: 2
Classifier: Programming Language :: Python :: 3
Requires-Dist: feedparser
Requires-Dist: html2text
Requires-Dist: importlib-resources
Requires-Dist: typing
